{"Mutoh":{"version":"1","initMiscMod":"0","improvedInitiative":"0","currentHealth":"16","maxHealth":"16","currentTempHP":"0","armorBonus":"10","shieldBonus":"0","miscArmorBonus":"0","maxDex":"10","proficiencyBonus":"2","miscSpellAttackBonus":"0","miscSpellDCBonus":"0","castingStatCode":"4","offenseAbilityDisplay":"0","deathSaveSuccesses":"0","deathSaveFailures":"0","showDeathSaves":"true","baseSpeed":"30","speedMiscMod":"-10","movementMode":"Speed","raceCode":"-1","subraceCode":"-1","backgroundCode":"-1","pagePosition0":"1","pagePosition1":"2","pagePosition2":"3","pagePosition3":"4","pagePosition4":"5","unarmoredDefense":"0","classData":[["Druid","Circle of the Moon","2","0⊟⊟Resource","Resource","0","0","0","2","0","0","-1","0"],["Wild Shape","","2","2","0","1","0","0","303","0⊟⊟⊟⊟⊟Human⊟Human⊟Far Traveler⊟0"],"0","0","0","0","0","0","0","0","⊟0","0","0","0","0","0","0","0","0","⊟20","20","20","20","20","20","⊟0⊟2⊟0⊟1⊟1⊟1"],"weaponList":["2","Quarterstaff","5 feet","1100","0","0","0","0","0","true","true","1","1","6","Dagger","20/60","1101","1","0","0","0","0","true","true","1","1","4"],"abilityScores":{"str-score":"9","dex-score":"11","con-score":"13","int-score":"15","wis-score":"16","cha-score":"14","str-prof":"false","dex-prof":"false","con-prof":"false","int-prof":"true","wis-prof":"true","cha-prof":"false","str-bonus":"0","dex-bonus":"0","con-bonus":"0","int-bonus":"0","wis-bonus":"0","cha-bonus":"0"},"skillInfo":["false","false","false","false","false","false","false","true","false","false","true","false","true","true","false","false","false","false","false","0","0","0","0","0","0","0","0","0","0","0","0","0","0","0","0","0","0","0","false","false","false","false","false","false","false","false","false","false","false","false","false","false","false","false","false","false","false","false","false","false","false","false","false","false","false","false","false","false","false","false","false","false","false","false","false","false","false","false","false","false","false","false","false","false","false","false","false","false","false","false","false","false","false","false","false"],"spellList":["v1.1",["0","3","0","0","0","0","0","0","0","0",""],["true","true","false","false","false","false","false","false","false","false",""],["0","0","0","0","0","0","0","0","0",""],["0","0","0","0","0","0","0","0","0",""],"0","2","false",["0⊟Druidcraft⊟⊟⊟⊟⊟⊟true⊟0","0⊟Mending⊟⊟⊟⊟⊟⊟true⊟0","0⊟Mold Earth⊟⊟⊟⊟⊟⊟true⊟0","0⊟Shape Water⊟⊟⊟⊟⊟⊟true⊟0","1⊟Create or Destroy Water⊟⊟⊟⊟⊟⊟true⊟0","1⊟Entangle⊟⊟⊟⊟⊟⊟true⊟0","1⊟Goodberry⊟⊟⊟⊟⊟⊟true⊟0",""]],"noteList":{"features":"Human Features:\nFar Traveler Feature:\n• Your foreign nature can gain you access to those curious about your homeland\nDruid Features:\n• Understand a secret druid language\n• You can shapeshift into the form of a beast as an action (see rules)\n• Druid Archetype: Moon\n• You can wild shape as a bonus action, and can use up a spell slot to regain 1d8 hp per spell slot level as a bonus action while wild shaped\n• You can wild shape into beasts of CR equal to your druid level/3 (min 1)\n","armor-prof":"Light Armor, Medium Armor, Shields\n","weapon-prof":"Clubs, Daggers, Darts, Javelins, Maces, Quarterstaffs, Scimitars, Sickles, Slings, Spears\n","tool-prof":"Jaw harp\nHerbalism Kit\n","languages":"Common\nOrcish\nSign\nDruidic\n","equipment":"Leather belt\nLeather belt pouch\nQuarter staff (walking stick)\nSkinning dagger\nExplorer's pack (leather shoulder pouch)\nDruidic focus (frog skull)\nSilver necklace (with druidic focus)\nGray mantle, beige dress\nJaw harp\nMap of homeland","notes":"Village burned down by Orcish barbarians.\nParents killed, she was kidnapped.\nShipped off for slavery.\nTrained shape shifting and sign language with a friend.\nOne day they took the opportunity to escape, they transformed into spiders and crawled out off the cage.\nHer friend lost concentration, transformed back and was killed right there.\nNow she travels the world eager to learn anything that can aid her revenge.","class":"Druid 2","race":"Human","background":"Far Traveler","alignment":"","traits":"Good at hiding emotions\nTunnel vision when angry\nAfraid of fire\nNot keen on travelling on a big ship","ideals":"Information hungry, eager to learn","bonds":"Finding the people who captured her and burned her village","flaws":"Grown wary of Orcish and Barbaric looking people","name":"Gerda","class2":"Druid 2","cp":"0","sp":"0","ep":"0","gp":"5","pp":"0","zero":"0"},"hitDiceList":["1","2","8","2"],"classResource":["-1","-1","-1","-1","-1","-1","1","2","1000","3","4","5"]},"Sjenkie in een koelkast":{"version":"1","initMiscMod":"0","improvedInitiative":"0","currentHealth":"10","maxHealth":"10","currentTempHP":"0","armorBonus":"14","shieldBonus":"2","miscArmorBonus":"0","maxDex":"0","proficiencyBonus":"2","miscSpellAttackBonus":"0","miscSpellDCBonus":"0","castingStatCode":"4","offenseAbilityDisplay":"0","deathSaveSuccesses":"0","deathSaveFailures":"0","showDeathSaves":"true","baseSpeed":"35","speedMiscMod":"0","movementMode":"Speed","raceCode":"-1","subraceCode":"-1","backgroundCode":"-1","pagePosition0":"1","pagePosition1":"2","pagePosition2":"3","pagePosition3":"4","pagePosition4":"5","unarmoredDefense":"0","classData":[["Cleric","Life Domain","1","0⊟⊟Resource","Resource","0","0","0","2","0","0","303","0⊟⊟⊟⊟⊟Elf⊟Wood Elf⊟Acolyte⊟0"],"0","0","0","0","0","0","0","0","⊟0","0","0","0","0","0","0","0","0","⊟20","20","20","20","20","20","⊟0⊟2⊟0⊟1⊟1⊟3"],"weaponList":["2","Mace","5 feet","1100","0","0","0","0","0","true","true","1","1","6","Mace","5 feet","1100","0","0","0","0","0","true","true","1","1","6"],"abilityScores":{"str-score":"8","dex-score":"10","con-score":"15","int-score":"15","wis-score":"16","cha-score":"8","str-prof":"false","dex-prof":"false","con-prof":"false","int-prof":"false","wis-prof":"true","cha-prof":"true","str-bonus":"0","dex-bonus":"0","con-bonus":"0","int-bonus":"0","wis-bonus":"0","cha-bonus":"0"},"skillInfo":["false","false","false","false","false","true","false","false","true","false","true","true","true","false","false","false","false","false","false","0","0","0","0","0","0","0","0","0","0","0","0","0","0","0","0","0","0","0","false","false","false","false","false","false","false","false","false","false","false","false","false","false","false","false","false","false","false","false","false","false","false","false","false","false","false","false","false","false","false","false","false","false","false","false","false","false","false","false","false","false","false","false","false","false","false","false","false","false","false","false","false","false","false","false","false"],"spellList":["v1.1",["0","2","0","0","0","0","0","0","0","0",""],["true","true","false","false","false","false","false","false","false","false",""],["0","0","0","0","0","0","0","0","0",""],["0","0","0","0","0","0","0","0","0",""],"0","1","false",["1⊟Bless⊟⊟⊟⊟⊟⊟true⊟0","1⊟Cure Wounds⊟⊟⊟⊟⊟⊟true⊟0",""]],"noteList":{"features":"Elf Features:\n• Within 60 feet of you, treat dim light as bright, darkness as dim light\n• Immune to magical sleep, advantage on saves vs charmed\n• Meditating 4 hours counts as 8 hours of rest\n• Perception proficiency\n• Longsword, shortsword, shortbow, longbow proficiency\n• Can hide while lightly obscured by natural phenomena\nAcolyte Feature:\n• Receive aid from those who share your faith\nCleric Features:\n• Cleric Archetype: Life\n• Healing spells of at least 1st level heal an additional 2 + spell level\n","armor-prof":"Light Armor, Medium Armor, Shields\nHeavy Armor\n","weapon-prof":"Longsword\nShortsword\nShortbow\nLongbow\nSimple Weapons\n","tool-prof":"","languages":"Common\nElvish\nTwo Extra Languages\n","equipment":"scale mail\nshield\nmace\nmace\npriest's pouch\nholy symbol\nholy symbol\nprayer book\nstick of incense (5)\nvestments\nset of common clothes\nbelt pouch\n","notes":"","class":"Cleric 1","race":"Wood Elf","background":"Acolyte","alignment":"","traits":"","ideals":"","bonds":"","flaws":"","name":"Megorman","class2":"Cleric 1","cp":"0","sp":"0","ep":"0","gp":"15","pp":"0","zero":"0"},"hitDiceList":["1","1","8","1"],"classResource":["-1","-1","-1","-1","-1","-1","1","2","1000","3","4","5"]},"Marie":{"version":"1","initMiscMod":"0","improvedInitiative":"0","currentHealth":"18","maxHealth":"18","currentTempHP":"0","armorBonus":"11","shieldBonus":"0","miscArmorBonus":"0","maxDex":"10","proficiencyBonus":"2","miscSpellAttackBonus":"0","miscSpellDCBonus":"0","castingStatCode":"5","offenseAbilityDisplay":"0","deathSaveSuccesses":"0","deathSaveFailures":"0","showDeathSaves":"true","baseSpeed":"30","speedMiscMod":"0","movementMode":"Speed","raceCode":"-1","subraceCode":"-1","backgroundCode":"-1","pagePosition0":"1","pagePosition1":"2","pagePosition2":"3","pagePosition3":"4","pagePosition4":"5","unarmoredDefense":"0","classData":[["Warlock","The Hexblade","2","3⊟⊟Resource","Resource","0","0","0","2","0","0","303","0⊟⊟eldritch invocations","Gaze of Two Minds","Beguiling Influence⊟⊟⊟Tabaxi⊟⊟Charlatan⊟0"],"0","0","0","0","0","0","0","0","⊟0","0","0","0","0","0","0","0","0","⊟20","20","20","20","20","20","⊟0⊟2⊟0⊟1⊟1⊟1"],"weaponList":["3","Dart","30/120","2101","1","0","0","0","0","true","true","1","1","4","Light hammer","20/60","1100","0","0","0","0","0","true","true","1","1","4","Dagger","20/60","1101","0","0","0","0","0","true","true","1","1","4"],"abilityScores":{"str-score":"15","dex-score":"12","con-score":"12","int-score":"13","wis-score":"8","cha-score":"15","str-prof":"false","dex-prof":"false","con-prof":"false","int-prof":"false","wis-prof":"true","cha-prof":"true","str-bonus":"0","dex-bonus":"0","con-bonus":"0","int-bonus":"0","wis-bonus":"0","cha-bonus":"0"},"skillInfo":["false","false","true","true","true","false","false","true","false","false","false","false","true","false","true","false","false","true","false","0","0","0","0","0","0","0","0","0","0","0","0","0","0","0","0","0","0","0","false","false","false","false","false","false","false","false","false","false","false","false","false","false","false","false","false","false","false","false","false","false","false","false","false","false","false","false","false","false","false","false","false","false","false","false","false","false","false","false","false","false","false","false","false","false","false","false","false","false","false","false","false","false","false","false","false"],"spellList":["v1.1",["0","2","0","0","0","0","0","0","0","0",""],["false","false","false","false","false","false","false","false","false","false",""],["2","0","0","0","0","0","0","0","0",""],["2","0","0","0","0","0","0","0","0",""],"-1","0","false","⊟"],"noteList":{"features":"Tabaxi Features:\n• Within 60 feet of you, treat dim light as bright, darkness as dim light\n• You can double your speed for a turn when you move but must spend a turn not moving before using this again\n• You can claw as an unarmed attack for 1d4 slashing damage and can climb with a 20 speed\n\nCharlatan Feature:\n• You can forge documents after seeing an example to copy\n\nWarlock Features:\n• Warlock Archetype: Hexblade\n• The spells shield and wrathful smite are added to the warlock spell list for you\n• 1/rest as a bonus action you can curse a creature for 1 minute, healing level + Cha mod hp when it dies, critting it on a 19, and dealing it proficiency bonus extra damage\n• Gain martial weapon, shield, and medium armor proficiency\n• You can use Charisma for attack and damage rolls with your pact weapons and one one-handed weapon you choose at the start of each day\n• See Through Another: You can see/hear/etc through the senses of a creature you touch (see rules)\n• Sweet Talker: You are proficient in deception and persuasion\n","armor-prof":"Light Armor\nMedium Armor\nShields\n","weapon-prof":"Simple Weapons\nMartial Weapons\n","tool-prof":"Disguise kit\nForgery kit\n","languages":"Common\ngiant\n","equipment":"leather armor\ndart\nlight hammer\ndagger (2)\ncomponent pouch\ndungeoneer's pack\ndisguise kit\nsignet ring of fake duke\nset of fine clothes\nbelt pouch\n","notes":"","class":"Warlock 2","race":"Tabaxi","background":"Charlatan","alignment":"chaotic ","traits":"Whenever I come to a new place, I collect local rumors and spread gossip.\nI know a story relevant to almost every situation","ideals":"creativiteit, als ze het niet zien aankomen, heb je eig al gewonnen","bonds":"I've been searching my whole life for the answer to a certain question.","flaws":"ik wil wel is tijger doen als ik eig pussy ben","name":"Po","class2":"Warlock 2","cp":"0","sp":"0","ep":"0","gp":"15","pp":"0","zero":"0"},"hitDiceList":["1","2","8","2"],"classResource":["-1","-1","-1","-1","-1","-1","1","2","1000","3","4","5"]},"Coltrui":{"version":"1","initMiscMod":"0","improvedInitiative":"0","currentHealth":"15","maxHealth":"15","currentTempHP":"0","armorBonus":"11","shieldBonus":"2","miscArmorBonus":"0","maxDex":"10","proficiencyBonus":"2","miscSpellAttackBonus":"0","miscSpellDCBonus":"0","castingStatCode":"4","offenseAbilityDisplay":"0","deathSaveSuccesses":"0","deathSaveFailures":"0","showDeathSaves":"true","baseSpeed":"30","speedMiscMod":"0","movementMode":"Speed","raceCode":"-1","subraceCode":"-1","backgroundCode":"-1","pagePosition0":"1","pagePosition1":"2","pagePosition2":"3","pagePosition3":"4","pagePosition4":"5","unarmoredDefense":"0","classData":[["Druid","Circle of the Shepherd","2","0⊟⊟Resource","Resource","0","0","0","2","0","0","-1","0"],["Wild Shape","","2","2","0","1","0","0","303","0⊟⊟⊟⊟⊟Tortle⊟⊟Sailor⊟0"],"0","0","0","0","0","0","0","0","⊟0","0","0","0","0","0","0","0","0","⊟20","20","20","20","20","20","⊟0⊟2⊟0⊟1⊟1⊟1"],"weaponList":["1","Quarterstaff","5 feet","1100","0","0","0","0","0","true","true","1","1","6"],"abilityScores":{"str-score":"12","dex-score":"8","con-score":"12","int-score":"13","wis-score":"16","cha-score":"14","str-prof":"false","dex-prof":"false","con-prof":"false","int-prof":"true","wis-prof":"true","cha-prof":"false","str-bonus":"0","dex-bonus":"0","con-bonus":"0","int-bonus":"0","wis-bonus":"0","cha-bonus":"0"},"skillInfo":["true","false","false","false","false","false","false","true","false","true","false","false","true","true","false","false","false","false","false","0","0","0","0","0","0","0","0","0","0","0","0","0","0","0","0","0","0","0","false","false","false","false","false","false","false","false","false","false","false","false","false","false","false","false","false","false","false","false","false","false","false","false","false","false","false","false","false","false","false","false","false","false","false","false","false","false","false","false","false","false","false","false","false","false","false","false","false","false","false","false","false","false","false","false","false"],"spellList":["v1.1",["0","3","0","0","0","0","0","0","0","0",""],["false","false","false","false","false","false","false","false","false","false",""],["0","0","0","0","0","0","0","0","0",""],["0","0","0","0","0","0","0","0","0",""],"0","2","false","⊟"],"noteList":{"features":"Turtle Features:\n• You can claw as an unarmed attack for 1d4 slashing damage\n• You won't run out of breath for 60 minutes\n• You cannot wear armor and you gain no armor bonus from dexterity, but your base AC is 17\n• As an action you can drop prone, reduce your speed to 0, and have disadvantage on dex saves to gain advantage on con and str saves and +4 AC. Until you end this as a bonus action you cannot take any other action.\n• Survival proficiency\nSailor Feature:\n• You can arrange free passage on a ship for your party\nDruid Features:\n• Understand a secret druid language\n• You can shapeshift into the form of a beast as an action (see rules)\n• Druid Archetype: Shepherd\n• You know Sylvan and can speak with beasts (see rules)\n• As a bonus action you can create a 30 foot radius zone within 60 feet for 1 minute, than you can move 60 feet as a bonus action (1/rest)\n• When you create a zone it does one of: creatures you choose gain advantage on Str saves and checks and 5 + level temp hp, advantage on perception and you can grant advantage on an attack in the zone as a reaction, or heal creaturs you choose in the zone level hp when you spend a spell slot on a healing spell and advantage to detect creatures in the zone\n","armor-prof":"Light Armor, Medium Armor, Shields\n","weapon-prof":"Clubs, Daggers, Darts, Javelins, Maces, Quarterstaffs, Scimitars, Sickles, Slings, Spears\n","tool-prof":"Navigator's tools\nVehicles (water)\nHerbalism Kit\n","languages":"Common\nAquan\nDruidic\nSylvan\n","equipment":"leather armor\nshield\nquarterstaff\nexplorer's pack\ndruidic focus\nbelaying pin (club)\n50 feet of silk rope\nlucky charm\nset of common clothes\nbelt pouch\n","notes":"","class":"Druid 2","race":"Turtle","background":"Sailor","alignment":"","traits":"meer feest is meer beter","ideals":"freedom chaotic. mans like swimin  ya feel bruv ","bonds":"ruthless pirates plunderend my ship and mans was like. wys bruv.   can badmon join the dan.","flaws":"als het rustig is en iets zit niet vast. its mine","name":"Coltrui","class2":"Druid 2","cp":"0","sp":"0","ep":"0","gp":"10","pp":"0","zero":"0"},"hitDiceList":["1","2","8","2"],"classResource":["-1","-1","-1","-1","-1","-1","1","2","1000","3","4","5"]},"Jeboi Jan":{"version":"1","initMiscMod":"0","improvedInitiative":"0","currentHealth":"26","maxHealth":"26","currentTempHP":"0","armorBonus":"16","shieldBonus":"2","miscArmorBonus":"1","maxDex":"0","proficiencyBonus":"2","miscSpellAttackBonus":"0","miscSpellDCBonus":"0","castingStatCode":"5","offenseAbilityDisplay":"0","deathSaveSuccesses":"0","deathSaveFailures":"0","showDeathSaves":"true","baseSpeed":"30","speedMiscMod":"0","movementMode":"Speed","raceCode":"-1","subraceCode":"-1","backgroundCode":"-1","pagePosition0":"1","pagePosition1":"2","pagePosition2":"3","pagePosition3":"4","pagePosition4":"5","unarmoredDefense":"0","classData":[["Paladin","","2","1⊟⊟Resource","Resource","0","0","0","2","0","0","-1","0"],["Lay on Hands","Lay Hands","10","10","0","2","0","0","303","0⊟⊟fighting style","Defense⊟⊟⊟Human⊟Human⊟Noble⊟0"],"0","0","0","0","0","0","0","0","⊟0","0","0","0","0","0","0","0","0","⊟20","20","20","20","20","20","⊟0⊟2⊟0⊟1⊟1⊟3"],"weaponList":["2","Javelin","30/120","1101","0","0","0","0","0","true","true","1","1","6","Longsword","5 feet","1102","0","0","0","0","0","true","true","1","1","8"],"abilityScores":{"str-score":"16","dex-score":"9","con-score":"16","int-score":"9","wis-score":"9","cha-score":"16","str-prof":"false","dex-prof":"false","con-prof":"false","int-prof":"false","wis-prof":"true","cha-prof":"true","str-bonus":"0","dex-bonus":"0","con-bonus":"0","int-bonus":"0","wis-bonus":"0","cha-bonus":"0"},"skillInfo":["false","false","false","false","false","true","false","false","true","false","false","false","false","false","false","true","false","true","false","0","0","0","0","0","0","0","0","0","0","0","0","0","0","0","0","0","0","0","false","false","false","false","false","false","false","false","false","false","false","false","false","false","false","false","false","false","false","false","false","false","false","false","false","false","false","false","false","false","false","false","false","false","false","false","false","false","false","false","false","false","false","false","false","false","false","false","false","false","false","false","false","false","false","false","false"],"spellList":["v1.1",["0","2","0","0","0","0","0","0","0","0",""],["false","false","false","false","false","false","false","false","false","false",""],["0","0","0","0","0","0","0","0","0",""],["0","0","0","0","0","0","0","0","0",""],"1","2","false","⊟"],"noteList":{"features":"Human Features:\nNoble Feature:\n• You can secure an audience with a local noble\nPaladin Features:\n• As an action, detect the location of any celestial, fiend or undead and any consecrated or desecrated place or object within 60 feet (1 + Cha mod per day)\n• Gain a reservoir of healing power (10hp), and as an action, you can heal a creature you touch by draining that power. You can also cure one poison or disease from the creature by sacrificing 5hp from the reservoir\n• Fighting Style - Defense: +1 to AC while wearing armor\n• You can sacrifice a spell slot to deal (1 + spell level)d8 radiant damage plus 1d8 extra damage vs undead/fiends, when you hit with a melee weapon attack\n","armor-prof":"Light Armor, Medium Armor, Heavy Armor, Shields\n","weapon-prof":"Simple Weapons, Martial Weapons\n","tool-prof":"set of dice\n","languages":"Common\ndwarvish\nelvish\n","equipment":"chain mail\nshield\nmartial weapon\njavelin (5)\npriest's pack\nholy symbol\nset of fine clothes\nsignet ring\nscroll of pedigree\npurse\n","notes":"","class":"Paladin 2","race":"Human","background":"Noble","alignment":"chaotic good","traits":"\nNo one could doubt by looking at my regal bearing that I am a cut above the unwashed masses","ideals":"power","bonds":"My house’s alliance with another noble family must be sustained at all costs.","flaws":"\nI have an insatiable desire for carnal pleasures","name":"Dikpeert","class2":"Paladin 2","cp":"0","sp":"0","ep":"0","gp":"25","pp":"0","zero":"0"},"hitDiceList":["1","2","10","2"],"classResource":["-1","-1","-1","-1","-1","-1","1","2","1000","3","4","5"]},"Vonk     Freek Vonk":{"version":"1","initMiscMod":"0","improvedInitiative":"0","currentHealth":"26","maxHealth":"26","currentTempHP":"0","armorBonus":"16","shieldBonus":"2","miscArmorBonus":"1","maxDex":"0","proficiencyBonus":"2","miscSpellAttackBonus":"0","miscSpellDCBonus":"0","castingStatCode":"5","offenseAbilityDisplay":"0","deathSaveSuccesses":"0","deathSaveFailures":"0","showDeathSaves":"true","baseSpeed":"30","speedMiscMod":"0","movementMode":"Speed","raceCode":"-1","subraceCode":"-1","backgroundCode":"-1","pagePosition0":"1","pagePosition1":"2","pagePosition2":"3","pagePosition3":"4","pagePosition4":"5","unarmoredDefense":"0","classData":[["Paladin","","2","1⊟⊟Resource","Resource","0","0","0","2","0","0","-1","0"],["Lay on Hands","Lay Hands","10","10","0","2","0","0","303","0⊟⊟fighting style","Defense⊟⊟⊟Human⊟Human⊟Noble⊟0"],"0","0","0","0","0","0","0","0","⊟0","0","0","0","0","0","0","0","0","⊟20","20","20","20","20","20","⊟0⊟2⊟0⊟1⊟1⊟3"],"weaponList":["2","Javelin","30/120","1101","0","0","0","0","0","true","true","1","1","6","Longsword","5 feet","1102","0","0","0","0","0","true","true","1","1","8"],"abilityScores":{"str-score":"16","dex-score":"9","con-score":"16","int-score":"9","wis-score":"9","cha-score":"16","str-prof":"false","dex-prof":"false","con-prof":"false","int-prof":"false","wis-prof":"true","cha-prof":"true","str-bonus":"0","dex-bonus":"0","con-bonus":"0","int-bonus":"0","wis-bonus":"0","cha-bonus":"0"},"skillInfo":["false","false","false","false","false","true","false","false","true","false","false","false","false","false","false","true","false","true","false","0","0","0","0","0","0","0","0","0","0","0","0","0","0","0","0","0","0","0","false","false","false","false","false","false","false","false","false","false","false","false","false","false","false","false","false","false","false","false","false","false","false","false","false","false","false","false","false","false","false","false","false","false","false","false","false","false","false","false","false","false","false","false","false","false","false","false","false","false","false","false","false","false","false","false","false"],"spellList":["v1.1",["0","2","0","0","0","0","0","0","0","0",""],["false","false","false","false","false","false","false","false","false","false",""],["0","0","0","0","0","0","0","0","0",""],["0","0","0","0","0","0","0","0","0",""],"1","2","false","⊟"],"noteList":{"features":"Human Features:\nNoble Feature:\n• You can secure an audience with a local noble\nPaladin Features:\n• As an action, detect the location of any celestial, fiend or undead and any consecrated or desecrated place or object within 60 feet (1 + Cha mod per day)\n• Gain a reservoir of healing power (10hp), and as an action, you can heal a creature you touch by draining that power. You can also cure one poison or disease from the creature by sacrificing 5hp from the reservoir\n• Fighting Style - Defense: +1 to AC while wearing armor\n• You can sacrifice a spell slot to deal (1 + spell level)d8 radiant damage plus 1d8 extra damage vs undead/fiends, when you hit with a melee weapon attack\n","armor-prof":"Light Armor, Medium Armor, Heavy Armor, Shields\n","weapon-prof":"Simple Weapons, Martial Weapons\n","tool-prof":"set of dice\n","languages":"Common\ndwarvish\nelvish\n","equipment":"chain mail\nshield\nmartial weapon\njavelin (5)\npriest's pack\nholy symbol\nset of fine clothes\nsignet ring\nscroll of pedigree\npurse\n","notes":"","class":"Paladin 2","race":"Human","background":"Noble","alignment":"chaotic good","traits":"\nNo one could doubt by looking at my regal bearing that I am a cut above the unwashed masses","ideals":"power","bonds":"My house’s alliance with another noble family must be sustained at all costs.","flaws":"\nI have an insatiable desire for carnal pleasures","name":"Dikpeert","class2":"Paladin 2","cp":"0","sp":"0","ep":"0","gp":"25","pp":"0","zero":"0"},"hitDiceList":["1","2","10","2"],"classResource":["-1","-1","-1","-1","-1","-1","1","2","1000","3","4","5"]},"pjotr":{"version":"1","initMiscMod":"0","improvedInitiative":"0","currentHealth":"24","maxHealth":"24","currentTempHP":"0","armorBonus":"14","shieldBonus":"0","miscArmorBonus":"0","maxDex":"2","proficiencyBonus":"2","miscSpellAttackBonus":"0","miscSpellDCBonus":"0","castingStatCode":"4","offenseAbilityDisplay":"0","deathSaveSuccesses":"0","deathSaveFailures":"0","showDeathSaves":"true","baseSpeed":"30","speedMiscMod":"0","movementMode":"Speed","raceCode":"-1","subraceCode":"-1","backgroundCode":"-1","pagePosition0":"1","pagePosition1":"2","pagePosition2":"3","pagePosition3":"4","pagePosition4":"5","unarmoredDefense":"0","classData":[["Ranger","","2","1⊟⊟Resource","Resource","0","0","0","2","0","0","303","0⊟⊟fighting style","Archery⊟⊟⊟Elf⊟High Elf⊟Urchin⊟0"],"0","2","0","0","0","0","0","0","⊟0","0","0","0","0","0","0","0","0","⊟20","20","20","20","20","20","⊟0⊟2⊟0⊟1⊟1⊟2"],"weaponList":["3","Shortsword","5 feet","1101","1","0","0","0","0","true","true","1","1","6","Shortsword","5 feet","1101","1","0","0","0","0","true","true","1","1","6","Longbow","150/600","2201","1","0","0","0","0","true","true","1","1","8"],"abilityScores":{"str-score":"14","dex-score":"16","con-score":"14","int-score":"10","wis-score":"14","cha-score":"8","str-prof":"true","dex-prof":"true","con-prof":"false","int-prof":"false","wis-prof":"false","cha-prof":"false","str-bonus":"0","dex-bonus":"0","con-bonus":"0","int-bonus":"0","wis-bonus":"0","cha-bonus":"0"},"skillInfo":["true","false","true","true","false","false","false","false","false","true","false","false","true","true","false","false","false","false","false","0","0","0","0","0","0","0","0","0","0","0","0","0","0","0","0","0","0","0","false","false","false","false","false","false","false","false","false","false","false","false","false","false","false","false","false","false","false","false","false","false","false","false","false","false","false","false","false","false","false","false","false","false","false","false","false","false","false","false","false","false","false","false","false","false","false","false","false","false","false","false","false","false","false","false","false"],"spellList":["v1.1",["0","2","0","0","0","0","0","0","0","0",""],["false","false","false","false","false","false","false","false","false","false",""],["0","0","0","0","0","0","0","0","0",""],["0","0","0","0","0","0","0","0","0",""],"1","2","false","⊟"],"noteList":{"features":"Elf Features:\n• Within 60 feet of you, treat dim light as bright, darkness as dim light\n• Immune to magical sleep, advantage on saves vs charmed\n• Meditating 4 hours counts as 8 hours of rest\n• Perception proficiency\n• Longsword, shortsword, shortbow, longbow proficiency\n• Gain 1 wizard cantrip\nUrchin Feature:\n• Your party can travel through a city twice as fast when not in combat\nRanger Features:\n• Gain advantage on survival and Int checks concerning your chosen creature type, and you know a language spoken by those creatures\n• Gain advantage on Wis and Int checks concerning your chosen terrain, and bonuses while traveling through that terrain (flat ground)\n• Fighting Style - Archery: +2 to attack with ranged weapons\n","armor-prof":"Light Armor, Medium Armor, Shields\n","weapon-prof":"Longsword\nShortsword\nShortbow\nLongbow\nSimple Weapons, Martial Weapons\n","tool-prof":"Disguise kit\nThieves' tools\n","languages":"Common\nElvish\nGoblin\n","equipment":"scale mail\narrows (20)\nsmall knife\nmap of your home city\npet mouse\ntoken of your parents\nset of common clothes\nbelt pouch\na Backpack\na Crowbar\na Hammer\n10 pitons\n10 torches\na Tinderbox\n10 days of Rations\na Waterskin\n50 feet of Hempen rope\nsmall file\nset of lock picks\nsmall mirror\nset of narrow-bladed scissors\npair of pliers\n","notes":"Opgegroeid in een welgesteld gezin tussen de elven, maar ik werd afgestoten toen ik een half elf bleek te zijn. Uit noodzaak ben ik toen als dief op straat gaan leven.","class":"Ranger 2","race":"High Elf","background":"Urchin","alignment":"","traits":"\nI bluntly say what other people are hinting at or hiding.","ideals":"The rich need to be shown what life and death are like in the gutters.","bonds":"No one else should have to endure the hardships I've been through.","flaws":"\nI will never fully trust anyone other than myself.","name":"Erilandar Gresandoral","class2":"Ranger 2","cp":"0","sp":"0","ep":"0","gp":"10","pp":"0","zero":"0"},"hitDiceList":["1","2","10","2"],"classResource":["-1","-1","-1","-1","-1","-1","1","2","1000","3","4","5"]},"Stijn":{"version":"1","initMiscMod":"0","improvedInitiative":"0","currentHealth":"14","maxHealth":"14","currentTempHP":"0","armorBonus":"10","shieldBonus":"0","miscArmorBonus":"0","maxDex":"10","proficiencyBonus":"2","miscSpellAttackBonus":"0","miscSpellDCBonus":"0","castingStatCode":"3","offenseAbilityDisplay":"0","deathSaveSuccesses":"0","deathSaveFailures":"0","showDeathSaves":"true","baseSpeed":"25","speedMiscMod":"0","movementMode":"Speed","raceCode":"-1","subraceCode":"-1","backgroundCode":"-1","pagePosition0":"1","pagePosition1":"2","pagePosition2":"3","pagePosition3":"4","pagePosition4":"5","unarmoredDefense":"0","classData":[["Wizard","School of Evocation","2","0⊟⊟Resource","Resource","0","0","0","2","0","0","303","0⊟⊟⊟⊟⊟Halfling⊟Ghostwise Halfling⊟Haunted One⊟0"],"0","0","0","0","0","0","0","0","⊟0","0","0","0","0","0","0","0","0","⊟20","20","20","20","20","20","⊟0⊟2⊟0⊟1⊟1⊟0"],"weaponList":["1","Quarterstaff","5 feet","1100","0","0","0","0","0","true","true","1","1","6"],"abilityScores":{"str-score":"11","dex-score":"15","con-score":"10","int-score":"14","wis-score":"16","cha-score":"10","str-prof":"false","dex-prof":"false","con-prof":"false","int-prof":"true","wis-prof":"true","cha-prof":"false","str-bonus":"0","dex-bonus":"0","con-bonus":"0","int-bonus":"0","wis-bonus":"0","cha-bonus":"0"},"skillInfo":["false","false","false","false","true","true","true","false","false","false","true","false","false","false","false","false","false","false","false","0","0","0","0","0","0","0","0","0","0","0","0","0","0","0","0","0","0","0","false","false","false","false","false","false","false","false","false","false","false","false","false","false","false","false","false","false","false","false","false","false","false","false","false","false","false","false","false","false","false","false","false","false","false","false","false","false","false","false","false","false","false","false","false","false","false","false","false","false","false","false","false","false","false","false","false"],"spellList":["v1.1",["0","3","0","0","0","0","0","0","0","0",""],["false","false","false","false","false","false","false","false","false","false",""],["0","0","0","0","0","0","0","0","0",""],["0","0","0","0","0","0","0","0","0",""],"0","2","false","⊟"],"noteList":{"features":"Halfling Features:\n• Can reroll a natural 1\n• Advantage on saves vs frightened\n• Can move through larger creatures' spaces\n• Speak telepathically with one creature within 30 ft\nHaunted One Feature:\n• Commoners will do what they can to help you\nWizard Features:\n• Regain half your level (min 1) worth of spell slots during a short rest (once per day)\n• Wizard Archetype: Evocation\n• Half gold/time cost to copy school spells\n• Exclude 1 + spell level creatures from your evocations\n","armor-prof":"","weapon-prof":"Daggers, Darts, Slings, Quarterstaffs, Light Crossbows\n","tool-prof":"","languages":"Common\nHalfling\nOrcish\n","equipment":"quarterstaff\narcane focus\nscholar's pack\nspellbook\nset of common clothes\nmonster hunter's pack\nimportant trinket\n","notes":"","class":"Wizard 2","race":"Ghastly Halfling","background":"Haunted One","alignment":"Chaotic Good","traits":"I don't run from evil. Evil runs from me.","ideals":"I have a dark calling that puts me above the law.","bonds":"a terrible guilt consumes me. I hope that I can find redemption through my actions.","flaws":"I have an addiction","name":"Xero","class2":"Wizard 2","cp":"0","sp":"0","ep":"0","gp":"0","pp":"0","zero":"0"},"hitDiceList":["1","2","6","2"],"classResource":["-1","-1","-1","-1","-1","-1","1","2","1000","3","4","5"]},"Vonk     Freek":{"version":"1","initMiscMod":"0","improvedInitiative":"0","currentHealth":"26","maxHealth":"26","currentTempHP":"0","armorBonus":"16","shieldBonus":"2","miscArmorBonus":"1","maxDex":"0","proficiencyBonus":"2","miscSpellAttackBonus":"0","miscSpellDCBonus":"0","castingStatCode":"5","offenseAbilityDisplay":"0","deathSaveSuccesses":"0","deathSaveFailures":"0","showDeathSaves":"true","baseSpeed":"30","speedMiscMod":"0","movementMode":"Speed","raceCode":"-1","subraceCode":"-1","backgroundCode":"-1","pagePosition0":"1","pagePosition1":"2","pagePosition2":"3","pagePosition3":"4","pagePosition4":"5","unarmoredDefense":"0","classData":[["Paladin","","2","1⊟⊟Resource","Resource","0","0","0","2","0","0","-1","0"],["Lay on Hands","Lay Hands","10","10","0","2","0","0","303","0⊟⊟fighting style","Defense⊟⊟⊟Human⊟Human⊟Noble⊟0"],"0","0","0","0","0","0","0","0","⊟0","0","0","0","0","0","0","0","0","⊟20","20","20","20","20","20","⊟0⊟2⊟0⊟1⊟1⊟3"],"weaponList":["2","Javelin","30/120","1101","0","0","0","0","0","true","true","1","1","6","Longsword","5 feet","1102","0","0","0","0","0","true","true","1","1","8"],"abilityScores":{"str-score":"16","dex-score":"9","con-score":"16","int-score":"9","wis-score":"9","cha-score":"16","str-prof":"false","dex-prof":"false","con-prof":"false","int-prof":"false","wis-prof":"true","cha-prof":"true","str-bonus":"0","dex-bonus":"0","con-bonus":"0","int-bonus":"0","wis-bonus":"0","cha-bonus":"0"},"skillInfo":["false","false","false","false","false","true","false","false","true","false","false","false","false","false","false","true","false","true","false","0","0","0","0","0","0","0","0","0","0","0","0","0","0","0","0","0","0","0","false","false","false","false","false","false","false","false","false","false","false","false","false","false","false","false","false","false","false","false","false","false","false","false","false","false","false","false","false","false","false","false","false","false","false","false","false","false","false","false","false","false","false","false","false","false","false","false","false","false","false","false","false","false","false","false","false"],"spellList":["v1.1",["0","2","0","0","0","0","0","0","0","0",""],["false","false","false","false","false","false","false","false","false","false",""],["0","0","0","0","0","0","0","0","0",""],["0","0","0","0","0","0","0","0","0",""],"1","2","false","⊟"],"noteList":{"features":"Human Features:\nNoble Feature:\n• You can secure an audience with a local noble\nPaladin Features:\n• As an action, detect the location of any celestial, fiend or undead and any consecrated or desecrated place or object within 60 feet (1 + Cha mod per day)\n• Gain a reservoir of healing power (10hp), and as an action, you can heal a creature you touch by draining that power. You can also cure one poison or disease from the creature by sacrificing 5hp from the reservoir\n• Fighting Style - Defense: +1 to AC while wearing armor\n• You can sacrifice a spell slot to deal (1 + spell level)d8 radiant damage plus 1d8 extra damage vs undead/fiends, when you hit with a melee weapon attack\n","armor-prof":"Light Armor, Medium Armor, Heavy Armor, Shields\n","weapon-prof":"Simple Weapons, Martial Weapons\n","tool-prof":"set of dice\n","languages":"Common\ndwarvish\nelvish\n","equipment":"chain mail\nshield\nmartial weapon\njavelin (5)\npriest's pack\nholy symbol\nset of fine clothes\nsignet ring\nscroll of pedigree\npurse\n","notes":"","class":"Paladin 2","race":"Human","background":"Noble","alignment":"chaotic good","traits":"\nNo one could doubt by looking at my regal bearing that I am a cut above the unwashed masses","ideals":"power","bonds":"My house’s alliance with another noble family must be sustained at all costs.","flaws":"\nI have an insatiable desire for carnal pleasures","name":"Dikpeert","class2":"Paladin 2","cp":"0","sp":"0","ep":"0","gp":"25","pp":"0","zero":"0"},"hitDiceList":["1","2","10","2"],"classResource":["-1","-1","-1","-1","-1","-1","1","2","1000","3","4","5"]}}